<?xml version="1.0" encoding="UTF-8" ?>

<Section xmlns="urn:com.io7m.structural:8:0"
         xmlns:xi="http://www.w3.org/2001/XInclude"
         title="show-metadata">

  <Subsection title="Name">
    <Paragraph>
      <Term type="command">show-metadata</Term> - Show metadata in texture files.
    </Paragraph>
  </Subsection>

  <Subsection title="Description">
    <Paragraph>
      The <Term type="command">show-metadata</Term> command displays metadata in texture files.
    </Paragraph>
    <FormalItem title="Parameters">
      <xi:include href="CLNCommandShowImageInfo.xml"/>
    </FormalItem>
    <Paragraph>
      The command displays the contents of the <LinkExternal
      target="https://www.io7m.com/software/calino/specification/index.xhtml#id_16fddeaf-9d7f-437b-8662-01e6975f6249">metadata section</LinkExternal>
      in the texture file, if one exists.
    </Paragraph>
  </Subsection>

  <Subsection title="Examples">
    <FormalItem title="Example" type="example">
      <Verbatim>
        <xi:include parse="text"
                    href="c-show-metadata-example.txt"/>
      </Verbatim>
    </FormalItem>
  </Subsection>

</Section>
