<?xml version="1.0" encoding="UTF-8" ?>

<Section title="Image Information"
         id="4ae63d09-ce2d-46d4-a8eb-f1f9ad382ee8"
         xmlns="urn:com.io7m.structural:8:0"
         xmlns:xi="http://www.w3.org/2001/XInclude">

  <Paragraph>
    An <Term type="term">image information</Term> value aggregates all of the image metadata described
    in this specification.
  </Paragraph>

  <FormalItem title="Image Information">
    <Verbatim><xi:include href="69.txt" parse="text"/></Verbatim>
  </FormalItem>

  <FormalItem title="Image Size">
    <Verbatim><xi:include href="73.txt" parse="text"/></Verbatim>
  </FormalItem>

  <Paragraph>
    The <Term type="expression">sizeX</Term>, <Term type="expression">sizeY</Term>, and
    <Term type="expression">sizeZ</Term> values declare the size of the image on the
    <Term type="expression">X</Term>, <Term type="expression">Y</Term>, and <Term type="expression">Z</Term>
    axes, respectively. All size values must be non-zero, and further restrictions may be placed on the
    size values by specific <Link target="17b69d69-176f-4db1-bab3-c1666ed58c5c">image</Link> types.
  </Paragraph>

</Section>
